wasapi_client.py
py_wasapi_client-1.1.0.data/scripts/wasapi_client.py
py_wasapi_client-1.1.0.dist-info/LICENSE
py_wasapi_client-1.1.0.dist-info/METADATA
py_wasapi_client-1.1.0.dist-info/WHEEL
py_wasapi_client-1.1.0.dist-info/entry_points.txt
py_wasapi_client-1.1.0.dist-info/top_level.txt
py_wasapi_client-1.1.0.dist-info/RECORD
