Metadata-Version: 2.1
Name: py-wasapi-client
Version: 1.1.0
Summary: A client for the Archive-It and Webrecorder WASAPI Data Transer API
Home-page: https://github.com/unt-libraries/py-wasapi-client
Author: University of North Texas Libraries
Author-email: lauren.ko@unt.edu
License: BSD
Platform: UNKNOWN
Classifier: Intended Audience :: System Administrators
Classifier: License :: OSI Approved :: BSD License
Classifier: Natural Language :: English
Classifier: Programming Language :: Python
Classifier: Programming Language :: Python :: 3.4
Classifier: Programming Language :: Python :: 3.5
Classifier: Programming Language :: Python :: 3.6
Classifier: Programming Language :: Python :: 3.7
Classifier: Topic :: Communications :: File Sharing
Requires-Dist: requests (>=2.18.1)
